{
  "prepare_queue": {
    "installed": [],
    "uninstalled": []
  },
  "config_munge": {
    "files": {}
  },
  "installed_plugins": {
    "cordova-plugin-whitelist": {
      "PACKAGE_NAME": "com.example.condroid"
    },
    "cordova-plugin-device-mrdo": {
      "PACKAGE_NAME": "com.example.condroid"
    },
    "cordova-plugin-bluetooth-serial": {
      "PACKAGE_NAME": "com.example.condroid"
    },
    "cordova-plugin-x-toast": {
      "PACKAGE_NAME": "com.example.condroid"
    },
    "cordova-plugin-context-menu": {
      "PACKAGE_NAME": "com.example.condroid"
    },
    "cordova-plugin-listpicker": {
      "PACKAGE_NAME": "com.example.condroid"
    },
    "cordova-plugin-geolocation": {
      "PACKAGE_NAME": "com.example.condroid"
    },
    "cordova-plugin-keyboard": {
      "PACKAGE_NAME": "com.example.condroid"
    },
    "cordova-plugin-appcenter-analytics": {
      "PACKAGE_NAME": "com.example.condroid"
    },
    "cordova-plugin-appcenter-crashes": {
      "PACKAGE_NAME": "com.example.condroid"
    }
  },
  "dependent_plugins": {
    "cordova-plugin-appcenter-shared": {
      "PACKAGE_NAME": "com.example.condroid"
    }
  }
}